rrt_ml/__init__.py
rrt_ml/run.py
rrt_ml/algorithms/base.py
rrt_ml/algorithms/rl.py
rrt_ml/algorithms/rrt.py
rrt_ml/algorithms/sl.py
rrt_ml/configs/best.yaml
rrt_ml/data/rl/distance/best/test.csv
rrt_ml/data/rl/distance/best/train.csv
rrt_ml/data/rl/distance/best/val.csv
rrt_ml/data/sl/narrow/_train.csv
rrt_ml/data/sl/narrow/_val.csv
rrt_ml/data/sl/narrow/change_data.py
rrt_ml/data/sl/narrow/train.csv
rrt_ml/data/sl/narrow/val.csv
rrt_ml/deps/libraries/python_robotics_reeds_shepp.py
rrt_ml/deps/libraries/__pycache__/python_robotics_reeds_shepp.cpython-310.pyc
rrt_ml/deps/libraries/mrl/__init__.py
rrt_ml/deps/libraries/mrl/agent_base.py
rrt_ml/deps/libraries/mrl/import_all.py
rrt_ml/deps/libraries/mrl/__pycache__/__init__.cpython-310.pyc
rrt_ml/deps/libraries/mrl/__pycache__/agent_base.cpython-310.pyc
rrt_ml/deps/libraries/mrl/algorithms/continuous_off_policy.py
rrt_ml/deps/libraries/mrl/algorithms/discrete_off_policy.py
rrt_ml/deps/libraries/mrl/algorithms/fixed_horizon_DDPG.py
rrt_ml/deps/libraries/mrl/algorithms/random_ensemble_DPG.py
rrt_ml/deps/libraries/mrl/algorithms/__pycache__/continuous_off_policy.cpython-310.pyc
rrt_ml/deps/libraries/mrl/configs/continuous_off_policy.py
rrt_ml/deps/libraries/mrl/configs/discrete_off_policy.py
rrt_ml/deps/libraries/mrl/configs/make_continuous_agents.py
rrt_ml/deps/libraries/mrl/configs/__pycache__/continuous_off_policy.cpython-310.pyc
rrt_ml/deps/libraries/mrl/modules/action_noise.py
rrt_ml/deps/libraries/mrl/modules/curiosity.py
rrt_ml/deps/libraries/mrl/modules/density.py
rrt_ml/deps/libraries/mrl/modules/env.py
rrt_ml/deps/libraries/mrl/modules/eval.py
rrt_ml/deps/libraries/mrl/modules/goal_reward.py
rrt_ml/deps/libraries/mrl/modules/logging.py
rrt_ml/deps/libraries/mrl/modules/model.py
rrt_ml/deps/libraries/mrl/modules/normalizer.py
rrt_ml/deps/libraries/mrl/modules/success_prediction.py
rrt_ml/deps/libraries/mrl/modules/train.py
rrt_ml/deps/libraries/mrl/modules/__pycache__/action_noise.cpython-310.pyc
rrt_ml-0.0.8.dist-info/LICENSE
rrt_ml-0.0.8.dist-info/METADATA
rrt_ml-0.0.8.dist-info/WHEEL
rrt_ml-0.0.8.dist-info/entry_points.txt
rrt_ml-0.0.8.dist-info/top_level.txt
rrt_ml-0.0.8.dist-info/RECORD
