Metadata-Version: 2.1
Name: rrt-ml
Version: 0.0.8
Summary: Rapidly exploring random trees with machine learning
Author-email: Joao Pedro Barros Ferreira <jpuerj@gmail.com>
Project-URL: Homepage, https://github.com/ferreirajoaouerj/RRT-ML
Classifier: Programming Language :: Python :: 3
Classifier: License :: OSI Approved :: MIT License
Classifier: Operating System :: OS Independent
Requires-Python: >=3.10
License-File: LICENSE
Requires-Dist: pyyaml
Requires-Dist: joblib
Requires-Dist: matplotlib
Requires-Dist: numpy
Requires-Dist: pandas
Requires-Dist: rich
Requires-Dist: seaborn
Requires-Dist: optuna
Requires-Dist: scikit-learn
Requires-Dist: tensorboard
Requires-Dist: tbparse
Requires-Dist: do-mpc
Requires-Dist: scipy
Requires-Dist: pydantic
Requires-Dist: coral-pytorch
Requires-Dist: gekko
Requires-Dist: gym
Requires-Dist: dill
Requires-Dist: tabulate
